kerasadf/__init__.py
kerasadf/activations.py
kerasadf/layers/__init__.py
kerasadf/layers/convolutional.py
kerasadf/layers/core.py
kerasadf/layers/pooling.py
keras_adf-19.1.0.dist-info/LICENSE
keras_adf-19.1.0.dist-info/METADATA
keras_adf-19.1.0.dist-info/WHEEL
keras_adf-19.1.0.dist-info/top_level.txt
keras_adf-19.1.0.dist-info/RECORD
